setup.py
headintheclouds/__init__.py
headintheclouds/boot2docker.py
headintheclouds/cache.py
headintheclouds/docker.py
headintheclouds/ec2.py
headintheclouds/firewall.py
headintheclouds/gcp.py
headintheclouds/tasks.py
headintheclouds/unmanaged.py
headintheclouds/util.py
headintheclouds.egg-info/PKG-INFO
headintheclouds.egg-info/SOURCES.txt
headintheclouds.egg-info/dependency_links.txt
headintheclouds.egg-info/pbr.json
headintheclouds.egg-info/requires.txt
headintheclouds.egg-info/top_level.txt
headintheclouds/dependencies/__init__.py
headintheclouds/dependencies/PyDbLite/MySQL.py
headintheclouds/dependencies/PyDbLite/PyDbLite.py
headintheclouds/dependencies/PyDbLite/PyDbLiteConv.py
headintheclouds/dependencies/PyDbLite/PyDbLite_SQL.py
headintheclouds/dependencies/PyDbLite/PyDbLite_conversions.py
headintheclouds/dependencies/PyDbLite/SQLite.py
headintheclouds/dependencies/PyDbLite/__init__.py
headintheclouds/ensemble/__init__.py
headintheclouds/ensemble/container.py
headintheclouds/ensemble/create.py
headintheclouds/ensemble/dependency.py
headintheclouds/ensemble/dependencygraph.py
headintheclouds/ensemble/exceptions.py
headintheclouds/ensemble/firewall.py
headintheclouds/ensemble/parse.py
headintheclouds/ensemble/remote.py
headintheclouds/ensemble/server.py
headintheclouds/ensemble/tasks.py
headintheclouds/ensemble/thing.py
headintheclouds/ensemble/thingindex.py