Metadata-Version: 1.0
Name: headintheclouds
Version: 0.8.0
Summary: Provider-agnostic cloud provisioning and Docker orchestration
Home-page: https://github.com/andreasjansson/head-in-the-clouds
Author: Andreas Jansson
Author-email: andreas@jansson.me.uk
License: GNU GPLv3
Platform: UNKNOWN
